setup.cfg
setup.py
persper/__init__.py
persper.egg-info/PKG-INFO
persper.egg-info/SOURCES.txt
persper.egg-info/dependency_links.txt
persper.egg-info/top_level.txt