Metadata-Version: 1.0
Name: persper
Version: 0.0.0
Summary: Persper Library
Home-page: https://github.com/UltimateBeaver/persper
Author: ultimatebeaver
Author-email: yinhezheng1995@gmail.com
License: UNKNOWN
Keywords: open source,intellectual shareholding
Platform: UNKNOWN
